narrml/__init__.py
narrml-0.0.1.dist-info/METADATA
narrml-0.0.1.dist-info/WHEEL
narrml-0.0.1.dist-info/RECORD
