Metadata-Version: 2.3
Name: narrml
Version: 0.0.1
Summary: Narrative Markup Language - The open data format for visual narratives
License: MIT
Author: Scenium
Author-email: hello@scenium.ai
Requires-Python: >=3.13
Classifier: License :: OSI Approved :: MIT License
Classifier: Programming Language :: Python :: 3
Classifier: Programming Language :: Python :: 3.13
